[
  {
    "Key": "28143",
    "LocalizedName": "Dhaka",
    "EnglishName": "Dhaka",
    "Country": {
      "ID": "BD",
      "LocalizedName": "Bangladesh",
      "EnglishName": "Bangladesh"
    },
    "TimeZone": {
      "Code": "BDT",
      "Name": "Asia/Dhaka",
      "GmtOffset": 6,
      "IsDaylightSaving": false,
      "NextOffsetChange": null
    },
    "GeoPosition": {
      "Latitude": 23.7098,
      "Longitude": 90.40711,
      "Elevation": {
        "Metric": {
          "Value": 5,
          "Unit": "m",
          "UnitType": 5
        },
        "Imperial": {
          "Value": 16,
          "Unit": "ft",
          "UnitType": 0
        }
      }
    },
    "LocalObservationDateTime": "2020-05-28T13:35:00+06:00",
    "EpochTime": 1590651300,
    "WeatherText": "Mostly cloudy",
    "WeatherIcon": 6,
    "HasPrecipitation": false,
    "PrecipitationType": null,
    "IsDayTime": true,
    "Temperature": {
      "Metric": {
        "Value": 30,
        "Unit": "C",
        "UnitType": 17
      },
      "Imperial": {
        "Value": 86,
        "Unit": "F",
        "UnitType": 18
      }
    },
    "MobileLink": "http://m.accuweather.com/en/bd/dhaka/28143/current-weather/28143?lang=en-us",
    "Link": "http://www.accuweather.com/en/bd/dhaka/28143/current-weather/28143?lang=en-us"
  },
  {
    "Key": "113487",
    "LocalizedName": "Kinshasa",
    "EnglishName": "Kinshasa",
    "Country": {
      "ID": "CD",
      "LocalizedName": "Democratic Republic of the Congo",
      "EnglishName": "Democratic Republic of the Congo"
    },
    "TimeZone": {
      "Code": "WAT",
      "Name": "Africa/Kinshasa",
      "GmtOffset": 1,
      "IsDaylightSaving": false,
      "NextOffsetChange": null
    },
    "GeoPosition": {
      "Latitude": -4.31642,
      "Longitude": 15.29834,
      "Elevation": {
        "Metric": {
          "Value": 180,
          "Unit": "m",
          "UnitType": 5
        },
        "Imperial": {
          "Value": 590,
          "Unit": "ft",
          "UnitType": 0
        }
      }
    },
    "LocalObservationDateTime": "2020-05-28T08:22:00+01:00",
    "EpochTime": 1590650520,
    "WeatherText": "Clouds and sun",
    "WeatherIcon": 4,
    "HasPrecipitation": false,
    "PrecipitationType": null,
    "IsDayTime": true,
    "Temperature": {
      "Metric": {
        "Value": 26,
        "Unit": "C",
        "UnitType": 17
      },
      "Imperial": {
        "Value": 79,
        "Unit": "F",
        "UnitType": 18
      }
    },
    "MobileLink": "http://m.accuweather.com/en/cd/kinshasa/113487/current-weather/113487?lang=en-us",
    "Link": "http://www.accuweather.com/en/cd/kinshasa/113487/current-weather/113487?lang=en-us"
  },
  {
    "Key": "60449",
    "LocalizedName": "Santiago",
    "EnglishName": "Santiago",
    "Country": {
      "ID": "CL",
      "LocalizedName": "Chile",
      "EnglishName": "Chile"
    },
    "TimeZone": {
      "Code": "CLT",
      "Name": "America/Santiago",
      "GmtOffset": -4,
      "IsDaylightSaving": false,
      "NextOffsetChange": "2020-09-06T04:00:00Z"
    },
    "GeoPosition": {
      "Latitude": -33.44643,
      "Longitude": -70.65901,
      "Elevation": {
        "Metric": {
          "Value": 522,
          "Unit": "m",
          "UnitType": 5
        },
        "Imperial": {
          "Value": 1712,
          "Unit": "ft",
          "UnitType": 0
        }
      }
    },
    "LocalObservationDateTime": "2020-05-28T03:35:00-04:00",
    "EpochTime": 1590651300,
    "WeatherText": "Mostly clear",
    "WeatherIcon": 34,
    "HasPrecipitation": false,
    "PrecipitationType": null,
    "IsDayTime": false,
    "Temperature": {
      "Metric": {
        "Value": 10.6,
        "Unit": "C",
        "UnitType": 17
      },
      "Imperial": {
        "Value": 51,
        "Unit": "F",
        "UnitType": 18
      }
    },
    "MobileLink": "http://m.accuweather.com/en/cl/santiago/60449/current-weather/60449?lang=en-us",
    "Link": "http://www.accuweather.com/en/cl/santiago/60449/current-weather/60449?lang=en-us"
  },
  {
    "Key": "101924",
    "LocalizedName": "Beijing",
    "EnglishName": "Beijing",
    "Country": {
      "ID": "CN",
      "LocalizedName": "China",
      "EnglishName": "China"
    },
    "TimeZone": {
      "Code": "CST",
      "Name": "Asia/Shanghai",
      "GmtOffset": 8,
      "IsDaylightSaving": false,
      "NextOffsetChange": null
    },
    "GeoPosition": {
      "Latitude": 39.9173,
      "Longitude": 116.407066,
      "Elevation": {
        "Metric": {
          "Value": 62,
          "Unit": "m",
          "UnitType": 5
        },
        "Imperial": {
          "Value": 203,
          "Unit": "ft",
          "UnitType": 0
        }
      }
    },
    "LocalObservationDateTime": "2020-05-28T15:31:00+08:00",
    "EpochTime": 1590651060,
    "WeatherText": "Cloudy",
    "WeatherIcon": 7,
    "HasPrecipitation": false,
    "PrecipitationType": null,
    "LocalSource": {
      "Id": 7,
      "Name": "Huafeng",
      "WeatherCode": "01"
    },
    "IsDayTime": true,
    "Temperature": {
      "Metric": {
        "Value": 32.2,
        "Unit": "C",
        "UnitType": 17
      },
      "Imperial": {
        "Value": 90,
        "Unit": "F",
        "UnitType": 18
      }
    },
    "MobileLink": "http://m.accuweather.com/en/cn/beijing/101924/current-weather/101924?lang=en-us",
    "Link": "http://www.accuweather.com/en/cn/beijing/101924/current-weather/101924?lang=en-us"
  },
  {
    "Key": "107487",
    "LocalizedName": "Bogota",
    "EnglishName": "Bogota",
    "Country": {
      "ID": "CO",
      "LocalizedName": "Colombia",
      "EnglishName": "Colombia"
    },
    "TimeZone": {
      "Code": "COT",
      "Name": "America/Bogota",
      "GmtOffset": -5,
      "IsDaylightSaving": false,
      "NextOffsetChange": null
    },
    "GeoPosition": {
      "Latitude": 4.62836,
      "Longitude": -74.07677,
      "Elevation": {
        "Metric": {
          "Value": 2562,
          "Unit": "m",
          "UnitType": 5
        },
        "Imperial": {
          "Value": 8406,
          "Unit": "ft",
          "UnitType": 0
        }
      }
    },
    "LocalObservationDateTime": "2020-05-28T02:35:00-05:00",
    "EpochTime": 1590651300,
    "WeatherText": "Mostly cloudy",
    "WeatherIcon": 38,
    "HasPrecipitation": false,
    "PrecipitationType": null,
    "IsDayTime": false,
    "Temperature": {
      "Metric": {
        "Value": 9.5,
        "Unit": "C",
        "UnitType": 17
      },
      "Imperial": {
        "Value": 49,
        "Unit": "F",
        "UnitType": 18
      }
    },
    "MobileLink": "http://m.accuweather.com/en/co/bogota/107487/current-weather/107487?lang=en-us",
    "Link": "http://www.accuweather.com/en/co/bogota/107487/current-weather/107487?lang=en-us"
  },
  {
    "Key": "178087",
    "LocalizedName": "Berlin",
    "EnglishName": "Berlin",
    "Country": {
      "ID": "DE",
      "LocalizedName": "Germany",
      "EnglishName": "Germany"
    },
    "TimeZone": {
      "Code": "CEST",
      "Name": "Europe/Berlin",
      "GmtOffset": 2,
      "IsDaylightSaving": true,
      "NextOffsetChange": "2020-10-25T01:00:00Z"
    },
    "GeoPosition": {
      "Latitude": 52.51767,
      "Longitude": 13.40554,
      "Elevation": {
        "Metric": {
          "Value": 35,
          "Unit": "m",
          "UnitType": 5
        },
        "Imperial": {
          "Value": 114,
          "Unit": "ft",
          "UnitType": 0
        }
      }
    },
    "LocalObservationDateTime": "2020-05-28T09:36:00+02:00",
    "EpochTime": 1590651360,
    "WeatherText": "Mostly sunny",
    "WeatherIcon": 2,
    "HasPrecipitation": false,
    "PrecipitationType": null,
    "IsDayTime": true,
    "Temperature": {
      "Metric": {
        "Value": 13,
        "Unit": "C",
        "UnitType": 17
      },
      "Imperial": {
        "Value": 55,
        "Unit": "F",
        "UnitType": 18
      }
    },
    "MobileLink": "http://m.accuweather.com/en/de/berlin/10178/current-weather/178087?lang=en-us",
    "Link": "http://www.accuweather.com/en/de/berlin/10178/current-weather/178087?lang=en-us"
  },
  {
    "Key": "127164",
    "LocalizedName": "Cairo",
    "EnglishName": "Cairo",
    "Country": {
      "ID": "EG",
      "LocalizedName": "Egypt",
      "EnglishName": "Egypt"
    },
    "TimeZone": {
      "Code": "EET",
      "Name": "Africa/Cairo",
      "GmtOffset": 2,
      "IsDaylightSaving": false,
      "NextOffsetChange": null
    },
    "GeoPosition": {
      "Latitude": 30.08374,
      "Longitude": 31.25536,
      "Elevation": {
        "Metric": {
          "Value": 20,
          "Unit": "m",
          "UnitType": 5
        },
        "Imperial": {
          "Value": 65,
          "Unit": "ft",
          "UnitType": 0
        }
      }
    },
    "LocalObservationDateTime": "2020-05-28T09:22:00+02:00",
    "EpochTime": 1590650520,
    "WeatherText": "Mostly sunny",
    "WeatherIcon": 2,
    "HasPrecipitation": false,
    "PrecipitationType": null,
    "IsDayTime": true,
    "Temperature": {
      "Metric": {
        "Value": 23.8,
        "Unit": "C",
        "UnitType": 17
      },
      "Imperial": {
        "Value": 75,
        "Unit": "F",
        "UnitType": 18
      }
    },
    "MobileLink": "http://m.accuweather.com/en/eg/cairo/127164/current-weather/127164?lang=en-us",
    "Link": "http://www.accuweather.com/en/eg/cairo/127164/current-weather/127164?lang=en-us"
  },
  {
    "Key": "308526",
    "LocalizedName": "Madrid",
    "EnglishName": "Madrid",
    "Country": {
      "ID": "ES",
      "LocalizedName": "Spain",
      "EnglishName": "Spain"
    },
    "TimeZone": {
      "Code": "CEST",
      "Name": "Europe/Madrid",
      "GmtOffset": 2,
      "IsDaylightSaving": true,
      "NextOffsetChange": "2020-10-25T01:00:00Z"
    },
    "GeoPosition": {
      "Latitude": 40.4096,
      "Longitude": -3.68629,
      "Elevation": {
        "Metric": {
          "Value": 639,
          "Unit": "m",
          "UnitType": 5
        },
        "Imperial": {
          "Value": 2095,
          "Unit": "ft",
          "UnitType": 0
        }
      }
    },
    "LocalObservationDateTime": "2020-05-28T09:36:00+02:00",
    "EpochTime": 1590651360,
    "WeatherText": "Sunny",
    "WeatherIcon": 1,
    "HasPrecipitation": false,
    "PrecipitationType": null,
    "IsDayTime": true,
    "Temperature": {
      "Metric": {
        "Value": 18.4,
        "Unit": "C",
        "UnitType": 17
      },
      "Imperial": {
        "Value": 65,
        "Unit": "F",
        "UnitType": 18
      }
    },
    "MobileLink": "http://m.accuweather.com/en/es/madrid/308526/current-weather/308526?lang=en-us",
    "Link": "http://www.accuweather.com/en/es/madrid/308526/current-weather/308526?lang=en-us"
  },
  {
    "Key": "328328",
    "LocalizedName": "London",
    "EnglishName": "London",
    "Country": {
      "ID": "GB",
      "LocalizedName": "United Kingdom",
      "EnglishName": "United Kingdom"
    },
    "TimeZone": {
      "Code": "BST",
      "Name": "Europe/London",
      "GmtOffset": 1,
      "IsDaylightSaving": true,
      "NextOffsetChange": "2020-10-25T01:00:00Z"
    },
    "GeoPosition": {
      "Latitude": 51.51429,
      "Longitude": -0.10687,
      "Elevation": {
        "Metric": {
          "Value": 18,
          "Unit": "m",
          "UnitType": 5
        },
        "Imperial": {
          "Value": 59,
          "Unit": "ft",
          "UnitType": 0
        }
      }
    },
    "LocalObservationDateTime": "2020-05-28T08:36:00+01:00",
    "EpochTime": 1590651360,
    "WeatherText": "Mostly cloudy",
    "WeatherIcon": 6,
    "HasPrecipitation": false,
    "PrecipitationType": null,
    "IsDayTime": true,
    "Temperature": {
      "Metric": {
        "Value": 13.7,
        "Unit": "C",
        "UnitType": 17
      },
      "Imperial": {
        "Value": 57,
        "Unit": "F",
        "UnitType": 18
      }
    },
    "MobileLink": "http://m.accuweather.com/en/gb/london/ec4a-2/current-weather/328328?lang=en-us",
    "Link": "http://www.accuweather.com/en/gb/london/ec4a-2/current-weather/328328?lang=en-us"
  },
  {
    "Key": "182536",
    "LocalizedName": "Athens",
    "EnglishName": "Athens",
    "Country": {
      "ID": "GR",
      "LocalizedName": "Greece",
      "EnglishName": "Greece"
    },
    "TimeZone": {
      "Code": "EEST",
      "Name": "Europe/Athens",
      "GmtOffset": 3,
      "IsDaylightSaving": true,
      "NextOffsetChange": "2020-10-25T01:00:00Z"
    },
    "GeoPosition": {
      "Latitude": 37.98413,
      "Longitude": 23.72792,
      "Elevation": {
        "Metric": {
          "Value": 126,
          "Unit": "m",
          "UnitType": 5
        },
        "Imperial": {
          "Value": 413,
          "Unit": "ft",
          "UnitType": 0
        }
      }
    },
    "LocalObservationDateTime": "2020-05-28T10:36:00+03:00",
    "EpochTime": 1590651360,
    "WeatherText": "Partly sunny",
    "WeatherIcon": 3,
    "HasPrecipitation": false,
    "PrecipitationType": null,
    "IsDayTime": true,
    "Temperature": {
      "Metric": {
        "Value": 21.1,
        "Unit": "C",
        "UnitType": 17
      },
      "Imperial": {
        "Value": 70,
        "Unit": "F",
        "UnitType": 18
      }
    },
    "MobileLink": "http://m.accuweather.com/en/gr/athens/182536/current-weather/182536?lang=en-us",
    "Link": "http://www.accuweather.com/en/gr/athens/182536/current-weather/182536?lang=en-us"
  },
  {
    "Key": "1123655",
    "LocalizedName": "Hong Kong",
    "EnglishName": "Hong Kong",
    "Country": {
      "ID": "HK",
      "LocalizedName": "Hong Kong",
      "EnglishName": "Hong Kong"
    },
    "TimeZone": {
      "Code": "CST",
      "Name": "Asia/Hong_Kong",
      "GmtOffset": 8,
      "IsDaylightSaving": false,
      "NextOffsetChange": null
    },
    "GeoPosition": {
      "Latitude": 22.36851,
      "Longitude": 114.174019,
      "Elevation": {
        "Metric": {
          "Value": 35,
          "Unit": "m",
          "UnitType": 5
        },
        "Imperial": {
          "Value": 114,
          "Unit": "ft",
          "UnitType": 0
        }
      }
    },
    "LocalObservationDateTime": "2020-05-28T15:35:00+08:00",
    "EpochTime": 1590651300,
    "WeatherText": "Overcast",
    "WeatherIcon": 7,
    "HasPrecipitation": false,
    "PrecipitationType": null,
    "LocalSource": {
      "Id": 7,
      "Name": "Huafeng",
      "WeatherCode": "02"
    },
    "IsDayTime": true,
    "Temperature": {
      "Metric": {
        "Value": 30.9,
        "Unit": "C",
        "UnitType": 17
      },
      "Imperial": {
        "Value": 88,
        "Unit": "F",
        "UnitType": 18
      }
    },
    "MobileLink": "http://m.accuweather.com/en/hk/hong-kong/1123655/current-weather/1123655?lang=en-us",
    "Link": "http://www.accuweather.com/en/hk/hong-kong/1123655/current-weather/1123655?lang=en-us"
  },
  {
    "Key": "208971",
    "LocalizedName": "Jakarta",
    "EnglishName": "Jakarta",
    "Country": {
      "ID": "ID",
      "LocalizedName": "Indonesia",
      "EnglishName": "Indonesia"
    },
    "TimeZone": {
      "Code": "WIT",
      "Name": "Asia/Jakarta",
      "GmtOffset": 7,
      "IsDaylightSaving": false,
      "NextOffsetChange": null
    },
    "GeoPosition": {
      "Latitude": -6.17537,
      "Longitude": 106.8272,
      "Elevation": {
        "Metric": {
          "Value": 11,
          "Unit": "m",
          "UnitType": 5
        },
        "Imperial": {
          "Value": 35,
          "Unit": "ft",
          "UnitType": 0
        }
      }
    },
    "LocalObservationDateTime": "2020-05-28T14:40:00+07:00",
    "EpochTime": 1590651600,
    "WeatherText": "Partly sunny",
    "WeatherIcon": 3,
    "HasPrecipitation": false,
    "PrecipitationType": null,
    "IsDayTime": true,
    "Temperature": {
      "Metric": {
        "Value": 32.2,
        "Unit": "C",
        "UnitType": 17
      },
      "Imperial": {
        "Value": 90,
        "Unit": "F",
        "UnitType": 18
      }
    },
    "MobileLink": "http://m.accuweather.com/en/id/jakarta/208971/current-weather/208971?lang=en-us",
    "Link": "http://www.accuweather.com/en/id/jakarta/208971/current-weather/208971?lang=en-us"
  },
  {
    "Key": "202396",
    "LocalizedName": "Delhi",
    "EnglishName": "Delhi",
    "Country": {
      "ID": "IN",
      "LocalizedName": "India",
      "EnglishName": "India"
    },
    "TimeZone": {
      "Code": "IST",
      "Name": "Asia/Kolkata",
      "GmtOffset": 5.5,
      "IsDaylightSaving": false,
      "NextOffsetChange": null
    },
    "GeoPosition": {
      "Latitude": 28.64336,
      "Longitude": 77.11756,
      "Elevation": {
        "Metric": {
          "Value": 215,
          "Unit": "m",
          "UnitType": 5
        },
        "Imperial": {
          "Value": 705,
          "Unit": "ft",
          "UnitType": 0
        }
      }
    },
    "LocalObservationDateTime": "2020-05-28T13:05:00+05:30",
    "EpochTime": 1590651300,
    "WeatherText": "Mostly cloudy",
    "WeatherIcon": 6,
    "HasPrecipitation": false,
    "PrecipitationType": null,
    "IsDayTime": true,
    "Temperature": {
      "Metric": {
        "Value": 37.8,
        "Unit": "C",
        "UnitType": 17
      },
      "Imperial": {
        "Value": 100,
        "Unit": "F",
        "UnitType": 18
      }
    },
    "MobileLink": "http://m.accuweather.com/en/in/delhi/202396/current-weather/202396?lang=en-us",
    "Link": "http://www.accuweather.com/en/in/delhi/202396/current-weather/202396?lang=en-us"
  },
  {
    "Key": "207375",
    "LocalizedName": "Baghdad",
    "EnglishName": "Baghdad",
    "Country": {
      "ID": "IQ",
      "LocalizedName": "Iraq",
      "EnglishName": "Iraq"
    },
    "TimeZone": {
      "Code": "AST",
      "Name": "Asia/Baghdad",
      "GmtOffset": 3,
      "IsDaylightSaving": false,
      "NextOffsetChange": null
    },
    "GeoPosition": {
      "Latitude": 33.32815,
      "Longitude": 44.38603,
      "Elevation": {
        "Metric": {
          "Value": 35,
          "Unit": "m",
          "UnitType": 5
        },
        "Imperial": {
          "Value": 114,
          "Unit": "ft",
          "UnitType": 0
        }
      }
    },
    "LocalObservationDateTime": "2020-05-28T10:35:00+03:00",
    "EpochTime": 1590651300,
    "WeatherText": "Mostly sunny",
    "WeatherIcon": 2,
    "HasPrecipitation": false,
    "PrecipitationType": null,
    "IsDayTime": true,
    "Temperature": {
      "Metric": {
        "Value": 37.5,
        "Unit": "C",
        "UnitType": 17
      },
      "Imperial": {
        "Value": 99,
        "Unit": "F",
        "UnitType": 18
      }
    },
    "MobileLink": "http://m.accuweather.com/en/iq/baghdad/207375/current-weather/207375?lang=en-us",
    "Link": "http://www.accuweather.com/en/iq/baghdad/207375/current-weather/207375?lang=en-us"
  },
  {
    "Key": "226396",
    "LocalizedName": "Tokyo",
    "EnglishName": "Tokyo",
    "Country": {
      "ID": "JP",
      "LocalizedName": "Japan",
      "EnglishName": "Japan"
    },
    "TimeZone": {
      "Code": "JST",
      "Name": "Asia/Tokyo",
      "GmtOffset": 9,
      "IsDaylightSaving": false,
      "NextOffsetChange": null
    },
    "GeoPosition": {
      "Latitude": 35.68301,
      "Longitude": 139.809,
      "Elevation": {
        "Metric": {
          "Value": 1,
          "Unit": "m",
          "UnitType": 5
        },
        "Imperial": {
          "Value": 3,
          "Unit": "ft",
          "UnitType": 0
        }
      }
    },
    "LocalObservationDateTime": "2020-05-28T16:35:00+09:00",
    "EpochTime": 1590651300,
    "WeatherText": "Cloudy",
    "WeatherIcon": 7,
    "HasPrecipitation": false,
    "PrecipitationType": null,
    "IsDayTime": true,
    "Temperature": {
      "Metric": {
        "Value": 22.2,
        "Unit": "C",
        "UnitType": 17
      },
      "Imperial": {
        "Value": 72,
        "Unit": "F",
        "UnitType": 18
      }
    },
    "MobileLink": "http://m.accuweather.com/en/jp/tokyo/226396/current-weather/226396?lang=en-us",
    "Link": "http://www.accuweather.com/en/jp/tokyo/226396/current-weather/226396?lang=en-us"
  },
  {
    "Key": "226081",
    "LocalizedName": "Seoul",
    "EnglishName": "Seoul",
    "Country": {
      "ID": "KR",
      "LocalizedName": "South Korea",
      "EnglishName": "South Korea"
    },
    "TimeZone": {
      "Code": "KST",
      "Name": "Asia/Seoul",
      "GmtOffset": 9,
      "IsDaylightSaving": false,
      "NextOffsetChange": null
    },
    "GeoPosition": {
      "Latitude": 37.53703,
      "Longitude": 126.970078,
      "Elevation": {
        "Metric": {
          "Value": 19,
          "Unit": "m",
          "UnitType": 5
        },
        "Imperial": {
          "Value": 62,
          "Unit": "ft",
          "UnitType": 0
        }
      }
    },
    "LocalObservationDateTime": "2020-05-28T16:35:00+09:00",
    "EpochTime": 1590651300,
    "WeatherText": "Clouds and sun",
    "WeatherIcon": 4,
    "HasPrecipitation": false,
    "PrecipitationType": null,
    "IsDayTime": true,
    "Temperature": {
      "Metric": {
        "Value": 23.4,
        "Unit": "C",
        "UnitType": 17
      },
      "Imperial": {
        "Value": 74,
        "Unit": "F",
        "UnitType": 18
      }
    },
    "MobileLink": "http://m.accuweather.com/en/kr/seoul/226081/current-weather/226081?lang=en-us",
    "Link": "http://www.accuweather.com/en/kr/seoul/226081/current-weather/226081?lang=en-us"
  },
  {
    "Key": "242560",
    "LocalizedName": "Mexico City",
    "EnglishName": "Mexico City",
    "Country": {
      "ID": "MX",
      "LocalizedName": "Mexico",
      "EnglishName": "Mexico"
    },
    "TimeZone": {
      "Code": "CDT",
      "Name": "America/Mexico_City",
      "GmtOffset": -5,
      "IsDaylightSaving": true,
      "NextOffsetChange": "2020-10-25T07:00:00Z"
    },
    "GeoPosition": {
      "Latitude": 19.4334,
      "Longitude": -99.13318,
      "Elevation": {
        "Metric": {
          "Value": 2242,
          "Unit": "m",
          "UnitType": 5
        },
        "Imperial": {
          "Value": 7357,
          "Unit": "ft",
          "UnitType": 0
        }
      }
    },
    "LocalObservationDateTime": "2020-05-28T02:35:00-05:00",
    "EpochTime": 1590651300,
    "WeatherText": "Mostly cloudy",
    "WeatherIcon": 38,
    "HasPrecipitation": false,
    "PrecipitationType": null,
    "IsDayTime": false,
    "Temperature": {
      "Metric": {
        "Value": 20,
        "Unit": "C",
        "UnitType": 17
      },
      "Imperial": {
        "Value": 68,
        "Unit": "F",
        "UnitType": 18
      }
    },
    "MobileLink": "http://m.accuweather.com/en/mx/mexico-city/242560/current-weather/242560?lang=en-us",
    "Link": "http://www.accuweather.com/en/mx/mexico-city/242560/current-weather/242560?lang=en-us"
  },
  {
    "Key": "264120",
    "LocalizedName": "Lima",
    "EnglishName": "Lima",
    "Country": {
      "ID": "PE",
      "LocalizedName": "Peru",
      "EnglishName": "Peru"
    },
    "TimeZone": {
      "Code": "PET",
      "Name": "America/Lima",
      "GmtOffset": -5,
      "IsDaylightSaving": false,
      "NextOffsetChange": null
    },
    "GeoPosition": {
      "Latitude": -12.08236,
      "Longitude": -77.04538,
      "Elevation": {
        "Metric": {
          "Value": 105,
          "Unit": "m",
          "UnitType": 5
        },
        "Imperial": {
          "Value": 344,
          "Unit": "ft",
          "UnitType": 0
        }
      }
    },
    "LocalObservationDateTime": "2020-05-28T02:35:00-05:00",
    "EpochTime": 1590651300,
    "WeatherText": "Mostly cloudy",
    "WeatherIcon": 38,
    "HasPrecipitation": false,
    "PrecipitationType": null,
    "IsDayTime": false,
    "Temperature": {
      "Metric": {
        "Value": 17.9,
        "Unit": "C",
        "UnitType": 17
      },
      "Imperial": {
        "Value": 64,
        "Unit": "F",
        "UnitType": 18
      }
    },
    "MobileLink": "http://m.accuweather.com/en/pe/lima/264120/current-weather/264120?lang=en-us",
    "Link": "http://www.accuweather.com/en/pe/lima/264120/current-weather/264120?lang=en-us"
  },
  {
    "Key": "294021",
    "LocalizedName": "Moscow",
    "EnglishName": "Moscow",
    "Country": {
      "ID": "RU",
      "LocalizedName": "Russia",
      "EnglishName": "Russia"
    },
    "TimeZone": {
      "Code": "MSK",
      "Name": "Europe/Moscow",
      "GmtOffset": 3,
      "IsDaylightSaving": false,
      "NextOffsetChange": null
    },
    "GeoPosition": {
      "Latitude": 55.75162,
      "Longitude": 37.61871,
      "Elevation": {
        "Metric": {
          "Value": 155,
          "Unit": "m",
          "UnitType": 5
        },
        "Imperial": {
          "Value": 508,
          "Unit": "ft",
          "UnitType": 0
        }
      }
    },
    "LocalObservationDateTime": "2020-05-28T10:35:00+03:00",
    "EpochTime": 1590651300,
    "WeatherText": "Mostly sunny",
    "WeatherIcon": 2,
    "HasPrecipitation": false,
    "PrecipitationType": null,
    "IsDayTime": true,
    "Temperature": {
      "Metric": {
        "Value": 18.2,
        "Unit": "C",
        "UnitType": 17
      },
      "Imperial": {
        "Value": 65,
        "Unit": "F",
        "UnitType": 18
      }
    },
    "MobileLink": "http://m.accuweather.com/en/ru/moscow/294021/current-weather/294021?lang=en-us",
    "Link": "http://www.accuweather.com/en/ru/moscow/294021/current-weather/294021?lang=en-us"
  },
  {
    "Key": "297030",
    "LocalizedName": "Riyadh",
    "EnglishName": "Riyadh",
    "Country": {
      "ID": "SA",
      "LocalizedName": "Saudi Arabia",
      "EnglishName": "Saudi Arabia"
    },
    "TimeZone": {
      "Code": "AST",
      "Name": "Asia/Riyadh",
      "GmtOffset": 3,
      "IsDaylightSaving": false,
      "NextOffsetChange": null
    },
    "GeoPosition": {
      "Latitude": 24.64039,
      "Longitude": 46.7533,
      "Elevation": {
        "Metric": {
          "Value": 598,
          "Unit": "m",
          "UnitType": 5
        },
        "Imperial": {
          "Value": 1961,
          "Unit": "ft",
          "UnitType": 0
        }
      }
    },
    "LocalObservationDateTime": "2020-05-28T10:35:00+03:00",
    "EpochTime": 1590651300,
    "WeatherText": "Sunny",
    "WeatherIcon": 1,
    "HasPrecipitation": false,
    "PrecipitationType": null,
    "IsDayTime": true,
    "Temperature": {
      "Metric": {
        "Value": 37.8,
        "Unit": "C",
        "UnitType": 17
      },
      "Imperial": {
        "Value": 100,
        "Unit": "F",
        "UnitType": 18
      }
    },
    "MobileLink": "http://m.accuweather.com/en/sa/riyadh/297030/current-weather/297030?lang=en-us",
    "Link": "http://www.accuweather.com/en/sa/riyadh/297030/current-weather/297030?lang=en-us"
  },
  {
    "Key": "300597",
    "LocalizedName": "Singapore",
    "EnglishName": "Singapore",
    "Country": {
      "ID": "SG",
      "LocalizedName": "Singapore",
      "EnglishName": "Singapore"
    },
    "TimeZone": {
      "Code": "SGT",
      "Name": "Asia/Singapore",
      "GmtOffset": 8,
      "IsDaylightSaving": false,
      "NextOffsetChange": null
    },
    "GeoPosition": {
      "Latitude": 1.31056,
      "Longitude": 103.843193,
      "Elevation": {
        "Metric": {
          "Value": 13,
          "Unit": "m",
          "UnitType": 5
        },
        "Imperial": {
          "Value": 42,
          "Unit": "ft",
          "UnitType": 0
        }
      }
    },
    "LocalObservationDateTime": "2020-05-28T15:40:00+08:00",
    "EpochTime": 1590651600,
    "WeatherText": "Clouds and sun",
    "WeatherIcon": 4,
    "HasPrecipitation": false,
    "PrecipitationType": null,
    "IsDayTime": true,
    "Temperature": {
      "Metric": {
        "Value": 35,
        "Unit": "C",
        "UnitType": 17
      },
      "Imperial": {
        "Value": 95,
        "Unit": "F",
        "UnitType": 18
      }
    },
    "MobileLink": "http://m.accuweather.com/en/sg/singapore/300597/current-weather/300597?lang=en-us",
    "Link": "http://www.accuweather.com/en/sg/singapore/300597/current-weather/300597?lang=en-us"
  },
  {
    "Key": "318849",
    "LocalizedName": "Bangkok",
    "EnglishName": "Bangkok",
    "Country": {
      "ID": "TH",
      "LocalizedName": "Thailand",
      "EnglishName": "Thailand"
    },
    "TimeZone": {
      "Code": "ICT",
      "Name": "Asia/Bangkok",
      "GmtOffset": 7,
      "IsDaylightSaving": false,
      "NextOffsetChange": null
    },
    "GeoPosition": {
      "Latitude": 13.73077,
      "Longitude": 100.521011,
      "Elevation": {
        "Metric": {
          "Value": 2,
          "Unit": "m",
          "UnitType": 5
        },
        "Imperial": {
          "Value": 6,
          "Unit": "ft",
          "UnitType": 0
        }
      }
    },
    "LocalObservationDateTime": "2020-05-28T14:35:00+07:00",
    "EpochTime": 1590651300,
    "WeatherText": "Clouds and sun",
    "WeatherIcon": 4,
    "HasPrecipitation": false,
    "PrecipitationType": null,
    "IsDayTime": true,
    "Temperature": {
      "Metric": {
        "Value": 37,
        "Unit": "C",
        "UnitType": 17
      },
      "Imperial": {
        "Value": 99,
        "Unit": "F",
        "UnitType": 18
      }
    },
    "MobileLink": "http://m.accuweather.com/en/th/bangkok/318849/current-weather/318849?lang=en-us",
    "Link": "http://www.accuweather.com/en/th/bangkok/318849/current-weather/318849?lang=en-us"
  },
  {
    "Key": "353412",
    "LocalizedName": "Hanoi",
    "EnglishName": "Hanoi",
    "Country": {
      "ID": "VN",
      "LocalizedName": "Vietnam",
      "EnglishName": "Vietnam"
    },
    "TimeZone": {
      "Code": "ICT",
      "Name": "Asia/Ho_Chi_Minh",
      "GmtOffset": 7,
      "IsDaylightSaving": false,
      "NextOffsetChange": null
    },
    "GeoPosition": {
      "Latitude": 20.99896,
      "Longitude": 105.700043,
      "Elevation": {
        "Metric": {
          "Value": 19,
          "Unit": "m",
          "UnitType": 5
        },
        "Imperial": {
          "Value": 62,
          "Unit": "ft",
          "UnitType": 0
        }
      }
    },
    "LocalObservationDateTime": "2020-05-28T14:35:00+07:00",
    "EpochTime": 1590651300,
    "WeatherText": "Thunderstorm",
    "WeatherIcon": 15,
    "HasPrecipitation": true,
    "PrecipitationType": "Rain",
    "IsDayTime": true,
    "Temperature": {
      "Metric": {
        "Value": 30.6,
        "Unit": "C",
        "UnitType": 17
      },
      "Imperial": {
        "Value": 87,
        "Unit": "F",
        "UnitType": 18
      }
    },
    "MobileLink": "http://m.accuweather.com/en/vn/hanoi/353412/current-weather/353412?lang=en-us",
    "Link": "http://www.accuweather.com/en/vn/hanoi/353412/current-weather/353412?lang=en-us"
  },
  {
    "Key": "22889",
    "LocalizedName": "Sydney",
    "EnglishName": "Sydney",
    "Country": {
      "ID": "AU",
      "LocalizedName": "Australia",
      "EnglishName": "Australia"
    },
    "TimeZone": {
      "Code": "AEST",
      "Name": "Australia/Sydney",
      "GmtOffset": 10,
      "IsDaylightSaving": false,
      "NextOffsetChange": "2020-10-03T16:00:00Z"
    },
    "GeoPosition": {
      "Latitude": -33.8705,
      "Longitude": 151.208847,
      "Elevation": {
        "Metric": {
          "Value": 1,
          "Unit": "m",
          "UnitType": 5
        },
        "Imperial": {
          "Value": 3,
          "Unit": "ft",
          "UnitType": 0
        }
      }
    },
    "LocalObservationDateTime": "2020-05-28T17:40:00+10:00",
    "EpochTime": 1590651600,
    "WeatherText": "Mostly clear",
    "WeatherIcon": 34,
    "HasPrecipitation": false,
    "PrecipitationType": null,
    "IsDayTime": false,
    "Temperature": {
      "Metric": {
        "Value": 18.3,
        "Unit": "C",
        "UnitType": 17
      },
      "Imperial": {
        "Value": 65,
        "Unit": "F",
        "UnitType": 18
      }
    },
    "MobileLink": "http://m.accuweather.com/en/au/sydney/22889/current-weather/22889?lang=en-us",
    "Link": "http://www.accuweather.com/en/au/sydney/22889/current-weather/22889?lang=en-us"
  },
  {
    "Key": "106577",
    "LocalizedName": "Shanghai",
    "EnglishName": "Shanghai",
    "Country": {
      "ID": "CN",
      "LocalizedName": "China",
      "EnglishName": "China"
    },
    "TimeZone": {
      "Code": "CST",
      "Name": "Asia/Shanghai",
      "GmtOffset": 8,
      "IsDaylightSaving": false,
      "NextOffsetChange": null
    },
    "GeoPosition": {
      "Latitude": 31.23151,
      "Longitude": 121.444168,
      "Elevation": {
        "Metric": {
          "Value": 5,
          "Unit": "m",
          "UnitType": 5
        },
        "Imperial": {
          "Value": 16,
          "Unit": "ft",
          "UnitType": 0
        }
      }
    },
    "LocalObservationDateTime": "2020-05-28T15:31:00+08:00",
    "EpochTime": 1590651060,
    "WeatherText": "Cloudy",
    "WeatherIcon": 7,
    "HasPrecipitation": false,
    "PrecipitationType": null,
    "LocalSource": {
      "Id": 7,
      "Name": "Huafeng",
      "WeatherCode": "01"
    },
    "IsDayTime": true,
    "Temperature": {
      "Metric": {
        "Value": 31.1,
        "Unit": "C",
        "UnitType": 17
      },
      "Imperial": {
        "Value": 88,
        "Unit": "F",
        "UnitType": 18
      }
    },
    "MobileLink": "http://m.accuweather.com/en/cn/shanghai/106577/current-weather/106577?lang=en-us",
    "Link": "http://www.accuweather.com/en/cn/shanghai/106577/current-weather/106577?lang=en-us"
  },
  {
    "Key": "204108",
    "LocalizedName": "Bengaluru",
    "EnglishName": "Bengaluru",
    "Country": {
      "ID": "IN",
      "LocalizedName": "India",
      "EnglishName": "India"
    },
    "TimeZone": {
      "Code": "IST",
      "Name": "Asia/Kolkata",
      "GmtOffset": 5.5,
      "IsDaylightSaving": false,
      "NextOffsetChange": null
    },
    "GeoPosition": {
      "Latitude": 12.99083,
      "Longitude": 77.57857,
      "Elevation": {
        "Metric": {
          "Value": 913,
          "Unit": "m",
          "UnitType": 5
        },
        "Imperial": {
          "Value": 2997,
          "Unit": "ft",
          "UnitType": 0
        }
      }
    },
    "LocalObservationDateTime": "2020-05-28T13:05:00+05:30",
    "EpochTime": 1590651300,
    "WeatherText": "Clouds and sun",
    "WeatherIcon": 4,
    "HasPrecipitation": false,
    "PrecipitationType": null,
    "IsDayTime": true,
    "Temperature": {
      "Metric": {
        "Value": 29.8,
        "Unit": "C",
        "UnitType": 17
      },
      "Imperial": {
        "Value": 86,
        "Unit": "F",
        "UnitType": 18
      }
    },
    "MobileLink": "http://m.accuweather.com/en/in/bengaluru/204108/current-weather/204108?lang=en-us",
    "Link": "http://www.accuweather.com/en/in/bengaluru/204108/current-weather/204108?lang=en-us"
  },
  {
    "Key": "204842",
    "LocalizedName": "Mumbai",
    "EnglishName": "Mumbai",
    "Country": {
      "ID": "IN",
      "LocalizedName": "India",
      "EnglishName": "India"
    },
    "TimeZone": {
      "Code": "IST",
      "Name": "Asia/Kolkata",
      "GmtOffset": 5.5,
      "IsDaylightSaving": false,
      "NextOffsetChange": null
    },
    "GeoPosition": {
      "Latitude": 19.14308,
      "Longitude": 72.87849,
      "Elevation": {
        "Metric": {
          "Value": 47,
          "Unit": "m",
          "UnitType": 5
        },
        "Imperial": {
          "Value": 154,
          "Unit": "ft",
          "UnitType": 0
        }
      }
    },
    "LocalObservationDateTime": "2020-05-28T13:05:00+05:30",
    "EpochTime": 1590651300,
    "WeatherText": "Partly sunny",
    "WeatherIcon": 3,
    "HasPrecipitation": false,
    "PrecipitationType": null,
    "IsDayTime": true,
    "Temperature": {
      "Metric": {
        "Value": 32.8,
        "Unit": "C",
        "UnitType": 17
      },
      "Imperial": {
        "Value": 91,
        "Unit": "F",
        "UnitType": 18
      }
    },
    "MobileLink": "http://m.accuweather.com/en/in/mumbai/204842/current-weather/204842?lang=en-us",
    "Link": "http://www.accuweather.com/en/in/mumbai/204842/current-weather/204842?lang=en-us"
  },
  {
    "Key": "206690",
    "LocalizedName": "Kolkata",
    "EnglishName": "Kolkata",
    "Country": {
      "ID": "IN",
      "LocalizedName": "India",
      "EnglishName": "India"
    },
    "TimeZone": {
      "Code": "IST",
      "Name": "Asia/Kolkata",
      "GmtOffset": 5.5,
      "IsDaylightSaving": false,
      "NextOffsetChange": null
    },
    "GeoPosition": {
      "Latitude": 22.52648,
      "Longitude": 88.35336,
      "Elevation": {
        "Metric": {
          "Value": 16,
          "Unit": "m",
          "UnitType": 5
        },
        "Imperial": {
          "Value": 52,
          "Unit": "ft",
          "UnitType": 0
        }
      }
    },
    "LocalObservationDateTime": "2020-05-28T13:05:00+05:30",
    "EpochTime": 1590651300,
    "WeatherText": "Mostly cloudy",
    "WeatherIcon": 6,
    "HasPrecipitation": false,
    "PrecipitationType": null,
    "IsDayTime": true,
    "Temperature": {
      "Metric": {
        "Value": 26.5,
        "Unit": "C",
        "UnitType": 17
      },
      "Imperial": {
        "Value": 80,
        "Unit": "F",
        "UnitType": 18
      }
    },
    "MobileLink": "http://m.accuweather.com/en/in/kolkata/206690/current-weather/206690?lang=en-us",
    "Link": "http://www.accuweather.com/en/in/kolkata/206690/current-weather/206690?lang=en-us"
  },
  {
    "Key": "261158",
    "LocalizedName": "Karachi",
    "EnglishName": "Karachi",
    "Country": {
      "ID": "PK",
      "LocalizedName": "Pakistan",
      "EnglishName": "Pakistan"
    },
    "TimeZone": {
      "Code": "PKT",
      "Name": "Asia/Karachi",
      "GmtOffset": 5,
      "IsDaylightSaving": false,
      "NextOffsetChange": null
    },
    "GeoPosition": {
      "Latitude": 24.88978,
      "Longitude": 67.02851,
      "Elevation": {
        "Metric": {
          "Value": 11,
          "Unit": "m",
          "UnitType": 5
        },
        "Imperial": {
          "Value": 36,
          "Unit": "ft",
          "UnitType": 0
        }
      }
    },
    "LocalObservationDateTime": "2020-05-28T12:35:00+05:00",
    "EpochTime": 1590651300,
    "WeatherText": "Sunny",
    "WeatherIcon": 1,
    "HasPrecipitation": false,
    "PrecipitationType": null,
    "IsDayTime": true,
    "Temperature": {
      "Metric": {
        "Value": 35,
        "Unit": "C",
        "UnitType": 17
      },
      "Imperial": {
        "Value": 95,
        "Unit": "F",
        "UnitType": 18
      }
    },
    "MobileLink": "http://m.accuweather.com/en/pk/karachi/261158/current-weather/261158?lang=en-us",
    "Link": "http://www.accuweather.com/en/pk/karachi/261158/current-weather/261158?lang=en-us"
  },
  {
    "Key": "318251",
    "LocalizedName": "Istanbul",
    "EnglishName": "Istanbul",
    "Country": {
      "ID": "TR",
      "LocalizedName": "Turkey",
      "EnglishName": "Turkey"
    },
    "TimeZone": {
      "Code": "TRT",
      "Name": "Europe/Istanbul",
      "GmtOffset": 3,
      "IsDaylightSaving": false,
      "NextOffsetChange": null
    },
    "GeoPosition": {
      "Latitude": 41.01105,
      "Longitude": 28.9578,
      "Elevation": {
        "Metric": {
          "Value": 48,
          "Unit": "m",
          "UnitType": 5
        },
        "Imperial": {
          "Value": 157,
          "Unit": "ft",
          "UnitType": 0
        }
      }
    },
    "LocalObservationDateTime": "2020-05-28T10:35:00+03:00",
    "EpochTime": 1590651300,
    "WeatherText": "Clouds and sun",
    "WeatherIcon": 4,
    "HasPrecipitation": false,
    "PrecipitationType": null,
    "IsDayTime": true,
    "Temperature": {
      "Metric": {
        "Value": 16.4,
        "Unit": "C",
        "UnitType": 17
      },
      "Imperial": {
        "Value": 62,
        "Unit": "F",
        "UnitType": 18
      }
    },
    "MobileLink": "http://m.accuweather.com/en/tr/istanbul/318251/current-weather/318251?lang=en-us",
    "Link": "http://www.accuweather.com/en/tr/istanbul/318251/current-weather/318251?lang=en-us"
  },
  {
    "Key": "347625",
    "LocalizedName": "Los Angeles",
    "EnglishName": "Los Angeles",
    "Country": {
      "ID": "US",
      "LocalizedName": "United States",
      "EnglishName": "United States"
    },
    "TimeZone": {
      "Code": "PDT",
      "Name": "America/Los_Angeles",
      "GmtOffset": -7,
      "IsDaylightSaving": true,
      "NextOffsetChange": "2020-11-01T09:00:00Z"
    },
    "GeoPosition": {
      "Latitude": 34.05224,
      "Longitude": -118.2437,
      "Elevation": {
        "Metric": {
          "Value": 121,
          "Unit": "m",
          "UnitType": 5
        },
        "Imperial": {
          "Value": 396,
          "Unit": "ft",
          "UnitType": 0
        }
      }
    },
    "LocalObservationDateTime": "2020-05-28T00:38:00-07:00",
    "EpochTime": 1590651480,
    "WeatherText": "Mostly cloudy",
    "WeatherIcon": 38,
    "HasPrecipitation": false,
    "PrecipitationType": null,
    "IsDayTime": false,
    "Temperature": {
      "Metric": {
        "Value": 16.7,
        "Unit": "C",
        "UnitType": 17
      },
      "Imperial": {
        "Value": 62,
        "Unit": "F",
        "UnitType": 18
      }
    },
    "MobileLink": "http://m.accuweather.com/en/us/los-angeles-ca/90012/current-weather/347625?lang=en-us",
    "Link": "http://www.accuweather.com/en/us/los-angeles-ca/90012/current-weather/347625?lang=en-us"
  },
  {
    "Key": "349727",
    "LocalizedName": "New York",
    "EnglishName": "New York",
    "Country": {
      "ID": "US",
      "LocalizedName": "United States",
      "EnglishName": "United States"
    },
    "TimeZone": {
      "Code": "EDT",
      "Name": "America/New_York",
      "GmtOffset": -4,
      "IsDaylightSaving": true,
      "NextOffsetChange": "2020-11-01T06:00:00Z"
    },
    "GeoPosition": {
      "Latitude": 40.779,
      "Longitude": -73.969,
      "Elevation": {
        "Metric": {
          "Value": 8,
          "Unit": "m",
          "UnitType": 5
        },
        "Imperial": {
          "Value": 26,
          "Unit": "ft",
          "UnitType": 0
        }
      }
    },
    "LocalObservationDateTime": "2020-05-28T03:38:00-04:00",
    "EpochTime": 1590651480,
    "WeatherText": "Mostly cloudy",
    "WeatherIcon": 38,
    "HasPrecipitation": false,
    "PrecipitationType": null,
    "IsDayTime": false,
    "Temperature": {
      "Metric": {
        "Value": 17.8,
        "Unit": "C",
        "UnitType": 17
      },
      "Imperial": {
        "Value": 64,
        "Unit": "F",
        "UnitType": 18
      }
    },
    "MobileLink": "http://m.accuweather.com/en/us/new-york-ny/10007/current-weather/349727?lang=en-us",
    "Link": "http://www.accuweather.com/en/us/new-york-ny/10007/current-weather/349727?lang=en-us"
  },
  {
    "Key": "4361",
    "LocalizedName": "Kabul",
    "EnglishName": "Kabul",
    "Country": {
      "ID": "AF",
      "LocalizedName": "Afghanistan",
      "EnglishName": "Afghanistan"
    },
    "TimeZone": {
      "Code": "AFT",
      "Name": "Asia/Kabul",
      "GmtOffset": 4.5,
      "IsDaylightSaving": false,
      "NextOffsetChange": null
    },
    "GeoPosition": {
      "Latitude": 34.53091,
      "Longitude": 69.13675,
      "Elevation": {
        "Metric": {
          "Value": 1838,
          "Unit": "m",
          "UnitType": 5
        },
        "Imperial": {
          "Value": 6031,
          "Unit": "ft",
          "UnitType": 0
        }
      }
    },
    "LocalObservationDateTime": "2020-05-28T12:05:00+04:30",
    "EpochTime": 1590651300,
    "WeatherText": "Partly sunny",
    "WeatherIcon": 3,
    "HasPrecipitation": false,
    "PrecipitationType": null,
    "IsDayTime": true,
    "Temperature": {
      "Metric": {
        "Value": 28.9,
        "Unit": "C",
        "UnitType": 17
      },
      "Imperial": {
        "Value": 84,
        "Unit": "F",
        "UnitType": 18
      }
    },
    "MobileLink": "http://m.accuweather.com/en/af/kabul/4361/current-weather/4361?lang=en-us",
    "Link": "http://www.accuweather.com/en/af/kabul/4361/current-weather/4361?lang=en-us"
  },
  {
    "Key": "7894",
    "LocalizedName": "Buenos Aires",
    "EnglishName": "Buenos Aires",
    "Country": {
      "ID": "AR",
      "LocalizedName": "Argentina",
      "EnglishName": "Argentina"
    },
    "TimeZone": {
      "Code": "ART",
      "Name": "America/Argentina/Buenos_Aires",
      "GmtOffset": -3,
      "IsDaylightSaving": false,
      "NextOffsetChange": null
    },
    "GeoPosition": {
      "Latitude": -34.60757,
      "Longitude": -58.43709,
      "Elevation": {
        "Metric": {
          "Value": 19,
          "Unit": "m",
          "UnitType": 5
        },
        "Imperial": {
          "Value": 62,
          "Unit": "ft",
          "UnitType": 0
        }
      }
    },
    "LocalObservationDateTime": "2020-05-28T04:35:00-03:00",
    "EpochTime": 1590651300,
    "WeatherText": "Clear",
    "WeatherIcon": 33,
    "HasPrecipitation": false,
    "PrecipitationType": null,
    "IsDayTime": false,
    "Temperature": {
      "Metric": {
        "Value": 13.9,
        "Unit": "C",
        "UnitType": 17
      },
      "Imperial": {
        "Value": 57,
        "Unit": "F",
        "UnitType": 18
      }
    },
    "MobileLink": "http://m.accuweather.com/en/ar/buenos-aires/7894/current-weather/7894?lang=en-us",
    "Link": "http://www.accuweather.com/en/ar/buenos-aires/7894/current-weather/7894?lang=en-us"
  },
  {
    "Key": "122438",
    "LocalizedName": "Havana",
    "EnglishName": "Havana",
    "Country": {
      "ID": "CU",
      "LocalizedName": "Cuba",
      "EnglishName": "Cuba"
    },
    "TimeZone": {
      "Code": "CDT",
      "Name": "America/Havana",
      "GmtOffset": -4,
      "IsDaylightSaving": true,
      "NextOffsetChange": "2020-11-01T05:00:00Z"
    },
    "GeoPosition": {
      "Latitude": 23.1168,
      "Longitude": -82.38859,
      "Elevation": {
        "Metric": {
          "Value": 35,
          "Unit": "m",
          "UnitType": 5
        },
        "Imperial": {
          "Value": 114,
          "Unit": "ft",
          "UnitType": 0
        }
      }
    },
    "LocalObservationDateTime": "2020-05-28T03:35:00-04:00",
    "EpochTime": 1590651300,
    "WeatherText": "Clear",
    "WeatherIcon": 33,
    "HasPrecipitation": false,
    "PrecipitationType": null,
    "IsDayTime": false,
    "Temperature": {
      "Metric": {
        "Value": 25.2,
        "Unit": "C",
        "UnitType": 17
      },
      "Imperial": {
        "Value": 77,
        "Unit": "F",
        "UnitType": 18
      }
    },
    "MobileLink": "http://m.accuweather.com/en/cu/havana/122438/current-weather/122438?lang=en-us",
    "Link": "http://www.accuweather.com/en/cu/havana/122438/current-weather/122438?lang=en-us"
  },
  {
    "Key": "623",
    "LocalizedName": "Paris",
    "EnglishName": "Paris",
    "Country": {
      "ID": "FR",
      "LocalizedName": "France",
      "EnglishName": "France"
    },
    "TimeZone": {
      "Code": "CEST",
      "Name": "Europe/Paris",
      "GmtOffset": 2,
      "IsDaylightSaving": true,
      "NextOffsetChange": "2020-10-25T01:00:00Z"
    },
    "GeoPosition": {
      "Latitude": 48.857,
      "Longitude": 2.351,
      "Elevation": {
        "Metric": {
          "Value": 35,
          "Unit": "m",
          "UnitType": 5
        },
        "Imperial": {
          "Value": 114,
          "Unit": "ft",
          "UnitType": 0
        }
      }
    },
    "LocalObservationDateTime": "2020-05-28T09:36:00+02:00",
    "EpochTime": 1590651360,
    "WeatherText": "Sunny",
    "WeatherIcon": 1,
    "HasPrecipitation": false,
    "PrecipitationType": null,
    "IsDayTime": true,
    "Temperature": {
      "Metric": {
        "Value": 15.5,
        "Unit": "C",
        "UnitType": 17
      },
      "Imperial": {
        "Value": 60,
        "Unit": "F",
        "UnitType": 18
      }
    },
    "MobileLink": "http://m.accuweather.com/en/fr/paris/623/current-weather/623?lang=en-us",
    "Link": "http://www.accuweather.com/en/fr/paris/623/current-weather/623?lang=en-us"
  },
  {
    "Key": "210841",
    "LocalizedName": "Tehran",
    "EnglishName": "Tehran",
    "Country": {
      "ID": "IR",
      "LocalizedName": "Iran",
      "EnglishName": "Iran"
    },
    "TimeZone": {
      "Code": "IRDT",
      "Name": "Asia/Tehran",
      "GmtOffset": 4.5,
      "IsDaylightSaving": true,
      "NextOffsetChange": "2020-09-20T19:30:00Z"
    },
    "GeoPosition": {
      "Latitude": 35.70131,
      "Longitude": 51.40739,
      "Elevation": {
        "Metric": {
          "Value": 1227,
          "Unit": "m",
          "UnitType": 5
        },
        "Imperial": {
          "Value": 4027,
          "Unit": "ft",
          "UnitType": 0
        }
      }
    },
    "LocalObservationDateTime": "2020-05-28T12:05:00+04:30",
    "EpochTime": 1590651300,
    "WeatherText": "Partly sunny",
    "WeatherIcon": 3,
    "HasPrecipitation": false,
    "PrecipitationType": null,
    "IsDayTime": true,
    "Temperature": {
      "Metric": {
        "Value": 32.2,
        "Unit": "C",
        "UnitType": 17
      },
      "Imperial": {
        "Value": 90,
        "Unit": "F",
        "UnitType": 18
      }
    },
    "MobileLink": "http://m.accuweather.com/en/ir/tehran/210841/current-weather/210841?lang=en-us",
    "Link": "http://www.accuweather.com/en/ir/tehran/210841/current-weather/210841?lang=en-us"
  },
  {
    "Key": "264885",
    "LocalizedName": "Manila",
    "EnglishName": "Manila",
    "Country": {
      "ID": "PH",
      "LocalizedName": "Philippines",
      "EnglishName": "Philippines"
    },
    "TimeZone": {
      "Code": "PHT",
      "Name": "Asia/Manila",
      "GmtOffset": 8,
      "IsDaylightSaving": false,
      "NextOffsetChange": null
    },
    "GeoPosition": {
      "Latitude": 14.58992,
      "Longitude": 120.981537,
      "Elevation": {
        "Metric": {
          "Value": 2,
          "Unit": "m",
          "UnitType": 5
        },
        "Imperial": {
          "Value": 8,
          "Unit": "ft",
          "UnitType": 0
        }
      }
    },
    "LocalObservationDateTime": "2020-05-28T15:40:00+08:00",
    "EpochTime": 1590651600,
    "WeatherText": "Cloudy",
    "WeatherIcon": 7,
    "HasPrecipitation": false,
    "PrecipitationType": null,
    "IsDayTime": true,
    "Temperature": {
      "Metric": {
        "Value": 27.8,
        "Unit": "C",
        "UnitType": 17
      },
      "Imperial": {
        "Value": 82,
        "Unit": "F",
        "UnitType": 18
      }
    },
    "MobileLink": "http://m.accuweather.com/en/ph/manila/264885/current-weather/264885?lang=en-us",
    "Link": "http://www.accuweather.com/en/ph/manila/264885/current-weather/264885?lang=en-us"
  },
  {
    "Key": "298198",
    "LocalizedName": "Belgrade",
    "EnglishName": "Belgrade",
    "Country": {
      "ID": "RS",
      "LocalizedName": "Serbia",
      "EnglishName": "Serbia"
    },
    "TimeZone": {
      "Code": "CEST",
      "Name": "Europe/Belgrade",
      "GmtOffset": 2,
      "IsDaylightSaving": true,
      "NextOffsetChange": "2020-10-25T01:00:00Z"
    },
    "GeoPosition": {
      "Latitude": 44.81653,
      "Longitude": 20.4637,
      "Elevation": {
        "Metric": {
          "Value": 99,
          "Unit": "m",
          "UnitType": 5
        },
        "Imperial": {
          "Value": 324,
          "Unit": "ft",
          "UnitType": 0
        }
      }
    },
    "LocalObservationDateTime": "2020-05-28T09:36:00+02:00",
    "EpochTime": 1590651360,
    "WeatherText": "Mostly cloudy",
    "WeatherIcon": 6,
    "HasPrecipitation": false,
    "PrecipitationType": null,
    "IsDayTime": true,
    "Temperature": {
      "Metric": {
        "Value": 14.9,
        "Unit": "C",
        "UnitType": 17
      },
      "Imperial": {
        "Value": 59,
        "Unit": "F",
        "UnitType": 18
      }
    },
    "MobileLink": "http://m.accuweather.com/en/rs/belgrade/298198/current-weather/298198?lang=en-us",
    "Link": "http://www.accuweather.com/en/rs/belgrade/298198/current-weather/298198?lang=en-us"
  },
  {
    "Key": "297442",
    "LocalizedName": "Dakar",
    "EnglishName": "Dakar",
    "Country": {
      "ID": "SN",
      "LocalizedName": "Senegal",
      "EnglishName": "Senegal"
    },
    "TimeZone": {
      "Code": "GMT",
      "Name": "Africa/Dakar",
      "GmtOffset": 0,
      "IsDaylightSaving": false,
      "NextOffsetChange": null
    },
    "GeoPosition": {
      "Latitude": 14.68667,
      "Longitude": -17.45191,
      "Elevation": {
        "Metric": {
          "Value": 11,
          "Unit": "m",
          "UnitType": 5
        },
        "Imperial": {
          "Value": 36,
          "Unit": "ft",
          "UnitType": 0
        }
      }
    },
    "LocalObservationDateTime": "2020-05-28T07:22:00+00:00",
    "EpochTime": 1590650520,
    "WeatherText": "Mostly cloudy",
    "WeatherIcon": 6,
    "HasPrecipitation": false,
    "PrecipitationType": null,
    "IsDayTime": true,
    "Temperature": {
      "Metric": {
        "Value": 22.8,
        "Unit": "C",
        "UnitType": 17
      },
      "Imperial": {
        "Value": 73,
        "Unit": "F",
        "UnitType": 18
      }
    },
    "MobileLink": "http://m.accuweather.com/en/sn/dakar/297442/current-weather/297442?lang=en-us",
    "Link": "http://www.accuweather.com/en/sn/dakar/297442/current-weather/297442?lang=en-us"
  },
  {
    "Key": "315078",
    "LocalizedName": "Taipei City",
    "EnglishName": "Taipei City",
    "Country": {
      "ID": "TW",
      "LocalizedName": "Taiwan",
      "EnglishName": "Taiwan"
    },
    "TimeZone": {
      "Code": "CST",
      "Name": "Asia/Taipei",
      "GmtOffset": 8,
      "IsDaylightSaving": false,
      "NextOffsetChange": null
    },
    "GeoPosition": {
      "Latitude": 25.04838,
      "Longitude": 121.514412,
      "Elevation": {
        "Metric": {
          "Value": 8,
          "Unit": "m",
          "UnitType": 5
        },
        "Imperial": {
          "Value": 26,
          "Unit": "ft",
          "UnitType": 0
        }
      }
    },
    "LocalObservationDateTime": "2020-05-28T15:35:00+08:00",
    "EpochTime": 1590651300,
    "WeatherText": "Overcast",
    "WeatherIcon": 7,
    "HasPrecipitation": false,
    "PrecipitationType": null,
    "LocalSource": {
      "Id": 7,
      "Name": "Huafeng",
      "WeatherCode": "02"
    },
    "IsDayTime": true,
    "Temperature": {
      "Metric": {
        "Value": 25,
        "Unit": "C",
        "UnitType": 17
      },
      "Imperial": {
        "Value": 77,
        "Unit": "F",
        "UnitType": 18
      }
    },
    "MobileLink": "http://m.accuweather.com/en/tw/taipei-city/315078/current-weather/315078?lang=en-us",
    "Link": "http://www.accuweather.com/en/tw/taipei-city/315078/current-weather/315078?lang=en-us"
  },
  {
    "Key": "306633",
    "LocalizedName": "Cape Town",
    "EnglishName": "Cape Town",
    "Country": {
      "ID": "ZA",
      "LocalizedName": "South Africa",
      "EnglishName": "South Africa"
    },
    "TimeZone": {
      "Code": "SAST",
      "Name": "Africa/Johannesburg",
      "GmtOffset": 2,
      "IsDaylightSaving": false,
      "NextOffsetChange": null
    },
    "GeoPosition": {
      "Latitude": -33.97901,
      "Longitude": 18.4823,
      "Elevation": {
        "Metric": {
          "Value": 15,
          "Unit": "m",
          "UnitType": 5
        },
        "Imperial": {
          "Value": 49,
          "Unit": "ft",
          "UnitType": 0
        }
      }
    },
    "LocalObservationDateTime": "2020-05-28T09:22:00+02:00",
    "EpochTime": 1590650520,
    "WeatherText": "Rain",
    "WeatherIcon": 18,
    "HasPrecipitation": true,
    "PrecipitationType": "Rain",
    "IsDayTime": true,
    "Temperature": {
      "Metric": {
        "Value": 14.4,
        "Unit": "C",
        "UnitType": 17
      },
      "Imperial": {
        "Value": 58,
        "Unit": "F",
        "UnitType": 18
      }
    },
    "MobileLink": "http://m.accuweather.com/en/za/cape-town/306633/current-weather/306633?lang=en-us",
    "Link": "http://www.accuweather.com/en/za/cape-town/306633/current-weather/306633?lang=en-us"
  },
  {
    "Key": "45881",
    "LocalizedName": "So Paulo",
    "EnglishName": "So Paulo",
    "Country": {
      "ID": "BR",
      "LocalizedName": "Brazil",
      "EnglishName": "Brazil"
    },
    "TimeZone": {
      "Code": "BRT",
      "Name": "America/Sao_Paulo",
      "GmtOffset": -3,
      "IsDaylightSaving": false,
      "NextOffsetChange": null
    },
    "GeoPosition": {
      "Latitude": -23.56739,
      "Longitude": -46.57038,
      "Elevation": {
        "Metric": {
          "Value": 662,
          "Unit": "m",
          "UnitType": 5
        },
        "Imperial": {
          "Value": 2171,
          "Unit": "ft",
          "UnitType": 0
        }
      }
    },
    "LocalObservationDateTime": "2020-05-28T04:35:00-03:00",
    "EpochTime": 1590651300,
    "WeatherText": "Mostly clear",
    "WeatherIcon": 34,
    "HasPrecipitation": false,
    "PrecipitationType": null,
    "IsDayTime": false,
    "Temperature": {
      "Metric": {
        "Value": 10.1,
        "Unit": "C",
        "UnitType": 17
      },
      "Imperial": {
        "Value": 50,
        "Unit": "F",
        "UnitType": 18
      }
    },
    "MobileLink": "http://m.accuweather.com/en/br/sao-paulo/45881/current-weather/45881?lang=en-us",
    "Link": "http://www.accuweather.com/en/br/sao-paulo/45881/current-weather/45881?lang=en-us"
  },
  {
    "Key": "55488",
    "LocalizedName": "Toronto",
    "EnglishName": "Toronto",
    "Country": {
      "ID": "CA",
      "LocalizedName": "Canada",
      "EnglishName": "Canada"
    },
    "TimeZone": {
      "Code": "EDT",
      "Name": "America/Toronto",
      "GmtOffset": -4,
      "IsDaylightSaving": true,
      "NextOffsetChange": "2020-11-01T06:00:00Z"
    },
    "GeoPosition": {
      "Latitude": 43.64864,
      "Longitude": -79.38027,
      "Elevation": {
        "Metric": {
          "Value": 81,
          "Unit": "m",
          "UnitType": 5
        },
        "Imperial": {
          "Value": 265,
          "Unit": "ft",
          "UnitType": 0
        }
      }
    },
    "LocalObservationDateTime": "2020-05-28T03:38:00-04:00",
    "EpochTime": 1590651480,
    "WeatherText": "Mostly cloudy",
    "WeatherIcon": 38,
    "HasPrecipitation": false,
    "PrecipitationType": null,
    "IsDayTime": false,
    "Temperature": {
      "Metric": {
        "Value": 18.9,
        "Unit": "C",
        "UnitType": 17
      },
      "Imperial": {
        "Value": 66,
        "Unit": "F",
        "UnitType": 18
      }
    },
    "MobileLink": "http://m.accuweather.com/en/ca/toronto/m5h/current-weather/55488?lang=en-us",
    "Link": "http://www.accuweather.com/en/ca/toronto/m5h/current-weather/55488?lang=en-us"
  },
  {
    "Key": "225007",
    "LocalizedName": "Osaka-shi",
    "EnglishName": "Osaka-shi",
    "Country": {
      "ID": "JP",
      "LocalizedName": "Japan",
      "EnglishName": "Japan"
    },
    "TimeZone": {
      "Code": "JST",
      "Name": "Asia/Tokyo",
      "GmtOffset": 9,
      "IsDaylightSaving": false,
      "NextOffsetChange": null
    },
    "GeoPosition": {
      "Latitude": 34.6667,
      "Longitude": 135.5,
      "Elevation": {
        "Metric": {
          "Value": 4,
          "Unit": "m",
          "UnitType": 5
        },
        "Imperial": {
          "Value": 13,
          "Unit": "ft",
          "UnitType": 0
        }
      }
    },
    "LocalObservationDateTime": "2020-05-28T16:35:00+09:00",
    "EpochTime": 1590651300,
    "WeatherText": "Mostly sunny",
    "WeatherIcon": 2,
    "HasPrecipitation": false,
    "PrecipitationType": null,
    "IsDayTime": true,
    "Temperature": {
      "Metric": {
        "Value": 25.8,
        "Unit": "C",
        "UnitType": 17
      },
      "Imperial": {
        "Value": 78,
        "Unit": "F",
        "UnitType": 18
      }
    },
    "MobileLink": "http://m.accuweather.com/en/jp/osaka-shi/225007/current-weather/225007?lang=en-us",
    "Link": "http://www.accuweather.com/en/jp/osaka-shi/225007/current-weather/225007?lang=en-us"
  },
  {
    "Key": "213225",
    "LocalizedName": "Jerusalem",
    "EnglishName": "Jerusalem",
    "Country": {
      "ID": "IL",
      "LocalizedName": "Israel",
      "EnglishName": "Israel"
    },
    "TimeZone": {
      "Code": "IDT",
      "Name": "Asia/Jerusalem",
      "GmtOffset": 3,
      "IsDaylightSaving": true,
      "NextOffsetChange": "2020-10-24T23:00:00Z"
    },
    "GeoPosition": {
      "Latitude": 31.7736,
      "Longitude": 35.225,
      "Elevation": {
        "Metric": {
          "Value": 804,
          "Unit": "m",
          "UnitType": 5
        },
        "Imperial": {
          "Value": 2637,
          "Unit": "ft",
          "UnitType": 0
        }
      }
    },
    "LocalObservationDateTime": "2020-05-28T10:35:00+03:00",
    "EpochTime": 1590651300,
    "WeatherText": "Partly sunny",
    "WeatherIcon": 3,
    "HasPrecipitation": false,
    "PrecipitationType": null,
    "IsDayTime": true,
    "Temperature": {
      "Metric": {
        "Value": 20,
        "Unit": "C",
        "UnitType": 17
      },
      "Imperial": {
        "Value": 68,
        "Unit": "F",
        "UnitType": 18
      }
    },
    "MobileLink": "http://m.accuweather.com/en/il/jerusalem/213225/current-weather/213225?lang=en-us",
    "Link": "http://www.accuweather.com/en/il/jerusalem/213225/current-weather/213225?lang=en-us"
  },
  {
    "Key": "249758",
    "LocalizedName": "Amsterdam",
    "EnglishName": "Amsterdam",
    "Country": {
      "ID": "NL",
      "LocalizedName": "Netherlands",
      "EnglishName": "Netherlands"
    },
    "TimeZone": {
      "Code": "CEST",
      "Name": "Europe/Amsterdam",
      "GmtOffset": 2,
      "IsDaylightSaving": true,
      "NextOffsetChange": "2020-10-25T01:00:00Z"
    },
    "GeoPosition": {
      "Latitude": 52.37249,
      "Longitude": 4.90023,
      "Elevation": {
        "Metric": {
          "Value": -1,
          "Unit": "m",
          "UnitType": 5
        },
        "Imperial": {
          "Value": -3,
          "Unit": "ft",
          "UnitType": 0
        }
      }
    },
    "LocalObservationDateTime": "2020-05-28T09:36:00+02:00",
    "EpochTime": 1590651360,
    "WeatherText": "Mostly sunny",
    "WeatherIcon": 2,
    "HasPrecipitation": false,
    "PrecipitationType": null,
    "IsDayTime": true,
    "Temperature": {
      "Metric": {
        "Value": 13.9,
        "Unit": "C",
        "UnitType": 17
      },
      "Imperial": {
        "Value": 57,
        "Unit": "F",
        "UnitType": 18
      }
    },
    "MobileLink": "http://m.accuweather.com/en/nl/amsterdam/249758/current-weather/249758?lang=en-us",
    "Link": "http://www.accuweather.com/en/nl/amsterdam/249758/current-weather/249758?lang=en-us"
  },
  {
    "Key": "314929",
    "LocalizedName": "Stockholm",
    "EnglishName": "Stockholm",
    "Country": {
      "ID": "SE",
      "LocalizedName": "Sweden",
      "EnglishName": "Sweden"
    },
    "TimeZone": {
      "Code": "CEST",
      "Name": "Europe/Stockholm",
      "GmtOffset": 2,
      "IsDaylightSaving": true,
      "NextOffsetChange": "2020-10-25T01:00:00Z"
    },
    "GeoPosition": {
      "Latitude": 59.31434,
      "Longitude": 18.06856,
      "Elevation": {
        "Metric": {
          "Value": 39,
          "Unit": "m",
          "UnitType": 5
        },
        "Imperial": {
          "Value": 127,
          "Unit": "ft",
          "UnitType": 0
        }
      }
    },
    "LocalObservationDateTime": "2020-05-28T09:36:00+02:00",
    "EpochTime": 1590651360,
    "WeatherText": "Mostly sunny",
    "WeatherIcon": 2,
    "HasPrecipitation": false,
    "PrecipitationType": null,
    "IsDayTime": true,
    "Temperature": {
      "Metric": {
        "Value": 12.2,
        "Unit": "C",
        "UnitType": 17
      },
      "Imperial": {
        "Value": 54,
        "Unit": "F",
        "UnitType": 18
      }
    },
    "MobileLink": "http://m.accuweather.com/en/se/stockholm/314929/current-weather/314929?lang=en-us",
    "Link": "http://www.accuweather.com/en/se/stockholm/314929/current-weather/314929?lang=en-us"
  },
  {
    "Key": "348211",
    "LocalizedName": "Honolulu",
    "EnglishName": "Honolulu",
    "Country": {
      "ID": "US",
      "LocalizedName": "United States",
      "EnglishName": "United States"
    },
    "TimeZone": {
      "Code": "HST",
      "Name": "Pacific/Honolulu",
      "GmtOffset": -10,
      "IsDaylightSaving": false,
      "NextOffsetChange": null
    },
    "GeoPosition": {
      "Latitude": 21.32568,
      "Longitude": -157.845367,
      "Elevation": {
        "Metric": {
          "Value": 112,
          "Unit": "m",
          "UnitType": 5
        },
        "Imperial": {
          "Value": 367,
          "Unit": "ft",
          "UnitType": 0
        }
      }
    },
    "LocalObservationDateTime": "2020-05-27T21:38:00-10:00",
    "EpochTime": 1590651480,
    "WeatherText": "Mostly cloudy",
    "WeatherIcon": 38,
    "HasPrecipitation": false,
    "PrecipitationType": null,
    "IsDayTime": false,
    "Temperature": {
      "Metric": {
        "Value": 25,
        "Unit": "C",
        "UnitType": 17
      },
      "Imperial": {
        "Value": 77,
        "Unit": "F",
        "UnitType": 18
      }
    },
    "MobileLink": "http://m.accuweather.com/en/us/honolulu-hi/96817/current-weather/348211?lang=en-us",
    "Link": "http://www.accuweather.com/en/us/honolulu-hi/96817/current-weather/348211?lang=en-us"
  },
  {
    "Key": "190390",
    "LocalizedName": "Reykjavik",
    "EnglishName": "Reykjavik",
    "Country": {
      "ID": "IS",
      "LocalizedName": "Iceland",
      "EnglishName": "Iceland"
    },
    "TimeZone": {
      "Code": "GMT",
      "Name": "Atlantic/Reykjavik",
      "GmtOffset": 0,
      "IsDaylightSaving": false,
      "NextOffsetChange": null
    },
    "GeoPosition": {
      "Latitude": 64.13738,
      "Longitude": -21.90248,
      "Elevation": {
        "Metric": {
          "Value": 36,
          "Unit": "m",
          "UnitType": 5
        },
        "Imperial": {
          "Value": 118,
          "Unit": "ft",
          "UnitType": 0
        }
      }
    },
    "LocalObservationDateTime": "2020-05-28T07:36:00+00:00",
    "EpochTime": 1590651360,
    "WeatherText": "Cloudy",
    "WeatherIcon": 7,
    "HasPrecipitation": false,
    "PrecipitationType": null,
    "IsDayTime": true,
    "Temperature": {
      "Metric": {
        "Value": 8.9,
        "Unit": "C",
        "UnitType": 17
      },
      "Imperial": {
        "Value": 48,
        "Unit": "F",
        "UnitType": 18
      }
    },
    "MobileLink": "http://m.accuweather.com/en/is/reykjavik/190390/current-weather/190390?lang=en-us",
    "Link": "http://www.accuweather.com/en/is/reykjavik/190390/current-weather/190390?lang=en-us"
  }
]